LICENSE
MANIFEST.in
README.md
pyproject.toml
setup.py
sentimentizer/__init__.py
sentimentizer/config.py
sentimentizer/extractor.py
sentimentizer/loader.py
sentimentizer/tokenizer.py
sentimentizer/trainer.py
sentimentizer.egg-info/PKG-INFO
sentimentizer.egg-info/SOURCES.txt
sentimentizer.egg-info/dependency_links.txt
sentimentizer.egg-info/requires.txt
sentimentizer.egg-info/top_level.txt
sentimentizer/data/__init__.py
sentimentizer/data/weights.pth
sentimentizer/data/yelp.dictionary
sentimentizer/models/__init__.py
sentimentizer/models/decoder.py
sentimentizer/models/encoder.py
sentimentizer/models/rnn.py
tests/test_rnn.py