Metadata-Version: 2.1
Name: sentimentizer
Version: 0.6.5
Summary: straight forward rnn model
Author-email: Edward Yang <edwardpyang@gmail.com>
License: Copyright (c) 2018-Present Edward Yang
Keywords: rnn,pytorch,nlp,sentiment
Classifier: License :: OSI Approved :: MIT License
Classifier: Programming Language :: Python
Requires-Python: >=3.10
Provides-Extra: dev
License-File: LICENSE
